setup.py
django_tethne_client.egg-info/PKG-INFO
django_tethne_client.egg-info/SOURCES.txt
django_tethne_client.egg-info/dependency_links.txt
django_tethne_client.egg-info/requires.txt
django_tethne_client.egg-info/top_level.txt
tethneweb/__init__.py
tethneweb/classes.py
tethneweb/client.py
tethneweb/results.py
tethneweb/upload.py