Metadata-Version: 1.0
Name: django-tethne-client
Version: 0.2.6
Summary: Python client for django-tethne JSON API.
Home-page: http://diging.github.io/tethne/
Author: Erick Peirson
Author-email: erick [dot] peirson [at] asu [dot] edu
License: GNU GPL 3
Platform: UNKNOWN
